{
	"type": "GenericCrafter",
	"name": "Metal crusher",
	"description": "Crushes copper and lead into scrap.",
	"outputItem": {"item": "scrap", "amount":2},
	"size": 2,
	"hasPower": true,
	"hasLiquids": false,
        "hasItems": true,
	"craftTime": 30,
	"updateEffect": "mine",
	"consumes": {
		"power": 0.5,
		"items": {
                        "items":[
                       {"item":"copper"},
                       {"item":"lead"}
                      ]}
                },
	"requirements": [
		{ "item": "hardened-metaglaphite", "amount": 10 },
		{ "item": "silicon", "amount": 15 },
		{ "item": "titanium", "amount": 20 }
	],
	"category": "crafting",
	"research": "pulverizer",
	"idleSound": "respawning",
	"idleSoundVolume": 0.5
}
